LICENSE
README.md
pyproject.toml
glacier/__init__.py
glacier/core.py
glacier/docstring.py
glacier/misc.py
glacier-0.4.5.dist-info/METADATA
glacier-0.4.5.dist-info/WHEEL
glacier-0.4.5.dist-info/licenses/LICENSE
glacier-0.4.5.dist-info/RECORD
