Metadata-Version: 2.4
Name: glacier
Version: 0.4.5
Summary: Python CLI building library for minimalists
Project-URL: Homepage, https://github.com/relastle/glacier
Project-URL: Documentation, https://github.com/relastle/glacier
Project-URL: Repository, https://github.com/relastle/glacier
Author-email: Hiroki Konishi <relastle@gmail.com>
License: MIT
License-File: LICENSE
Requires-Python: >=3.9
Requires-Dist: click-help-colors>=0.9.4
Requires-Dist: click>=8.1.8
